{"zpid":"333606021","id":"333606021","rawHomeStatusCd":"ForSale","marketingStatusSimplifiedCd":"For Sale by Agent","imgSrc":"https:\/\/photos.zillowstatic.com\/fp\/56129075222eaa295ddb06f8f9f83c5e-p_e.jpg","hasImage":true,"detailUrl":"https:\/\/www.zillow.com\/homedetails\/133-Seaport-Blvd-920-Boston-MA-02210\/333606021_zpid\/","statusType":"FOR_SALE","statusText":"Condo for sale","countryCurrency":"$","price":"$2,499,000","unformattedPrice":2499000,"address":"133 Seaport Blvd #920, Boston, MA 02210","addressStreet":"133 Seaport Blvd #920","addressCity":"Boston","addressState":"MA","addressZipcode":"02210","isUndisclosedAddress":false,"beds":2,"baths":3,"area":1255,"latLong":{"latitude":42.350525,"longitude":-71.0436},"isZillowOwned":false,"flexFieldText":"37 days on Zillow","flexFieldType":"daysOnZillow","hdpData":{"homeInfo":{"zpid":333606021,"streetAddress":"133 Seaport Blvd #920","zipcode":"02210","city":"Boston","state":"MA","latitude":42.350525,"longitude":-71.0436,"price":2499000,"bathrooms":3,"bedrooms":2,"livingArea":1255,"homeType":"CONDO","homeStatus":"FOR_SALE","daysOnZillow":38,"isFeatured":false,"shouldHighlight":false,"zestimate":2407600,"rentZestimate":10099,"listing_sub_type":{"is_FSBA":true},"isUnmappable":false,"isPreforeclosureAuction":false,"homeStatusForHDP":"FOR_SALE","priceForHDP":2499000,"timeOnZillow":3335107000,"isNonOwnerOccupied":true,"isPremierBuilder":false,"isZillowOwned":false,"currency":"USD","country":"USA","taxAssessedValue":1883000,"unit":"# 920","isShowcaseListing":false}},"isSaved":false,"isUserClaimingOwner":false,"isUserConfirmedClaim":false,"pgapt":"ForSale","sgapt":"For Sale (Broker)","zestimate":2407600.0,"shouldShowZestimateAsPrice":false,"has3DModel":false,"hasVideo":false,"isHomeRec":false,"hasAdditionalAttributions":true,"isFeaturedListing":false,"isShowcaseListing":false,"list":true,"relaxed":false,"info6String":"The Entwistle Group","brokerName":"Cityscapes International Realty","carouselPhotos":[{"url":"https:\/\/photos.zillowstatic.com\/fp\/56129075222eaa295ddb06f8f9f83c5e-p_e.jpg"},{"url":"https:\/\/photos.zillowstatic.com\/fp\/e899830a08bfeee2ce7b7c3b81aa8d63-p_e.jpg"},{"url":"https:\/\/photos.zillowstatic.com\/fp\/6dd8ba5c0c7a5af23a4ac6bf8e6c3943-p_e.jpg"},{"url":"https:\/\/photos.zillowstatic.com\/fp\/b40c85a2346de6a14036644bef775d47-p_e.jpg"},{"url":"https:\/\/photos.zillowstatic.com\/fp\/b5b9474156798a237ab82f26f9182c0b-p_e.jpg"},{"url":"https:\/\/photos.zillowstatic.com\/fp\/2dad668b484cf4676a0eece0412d1bd3-p_e.jpg"},{"url":"https:\/\/photos.zillowstatic.com\/fp\/23cc763b83020236013e91c6bafdbd80-p_e.jpg"},{"url":"https:\/\/photos.zillowstatic.com\/fp\/fee67445caf3437a5800348e3967ccf4-p_e.jpg"},{"url":"https:\/\/photos.zillowstatic.com\/fp\/ed77d32777e4a3781b8cd15d9ecea2d5-p_e.jpg"},{"url":"https:\/\/photos.zillowstatic.com\/fp\/8578cd2a6d59f2764e9710edff23e26e-p_e.jpg"},{"url":"https:\/\/photos.zillowstatic.com\/fp\/b4cbbde432edc26167da7c5a35fa7d3a-p_e.jpg"},{"url":"https:\/\/photos.zillowstatic.com\/fp\/17918b01fab916782a3d33d98bea214c-p_e.jpg"},{"url":"https:\/\/photos.zillowstatic.com\/fp\/c35577f2fd2bc656a1a3d4140d24e45b-p_e.jpg"},{"url":"https:\/\/photos.zillowstatic.com\/fp\/1e51e4951cb858cbd9de953b14ca4cdd-p_e.jpg"},{"url":"https:\/\/photos.zillowstatic.com\/fp\/7c16737d3e5b8e4ad324ae82effa530e-p_e.jpg"},{"url":"https:\/\/photos.zillowstatic.com\/fp\/810f956d9e57de0bc48ae1a1f8f98cf4-p_e.jpg"},{"url":"https:\/\/photos.zillowstatic.com\/fp\/261f1394c35349057b212bea5c688b58-p_e.jpg"},{"url":"https:\/\/photos.zillowstatic.com\/fp\/288d9265324350ddc55ba348bbbd2406-p_e.jpg"},{"url":"https:\/\/photos.zillowstatic.com\/fp\/b4f3539764a327b41a4f1df25005f12b-p_e.jpg"},{"url":"https:\/\/photos.zillowstatic.com\/fp\/cb868e9c79b376f6305640f344dcce7b-p_e.jpg"},{"url":"https:\/\/photos.zillowstatic.com\/fp\/3200180b7ebca2d04172ce9b86bb3b0f-p_e.jpg"},{"url":"https:\/\/photos.zillowstatic.com\/fp\/566d33367b46bd5adcec942d75386603-p_e.jpg"},{"url":"https:\/\/photos.zillowstatic.com\/fp\/4f3af1db717ea1d80c83ddbe357f1a43-p_e.jpg"},{"url":"https:\/\/photos.zillowstatic.com\/fp\/1726e9b322c267adc5a5399c52b088c0-p_e.jpg"},{"url":"https:\/\/photos.zillowstatic.com\/fp\/90cb2fa98c2702620fee984b14fb85eb-p_e.jpg"},{"url":"https:\/\/photos.zillowstatic.com\/fp\/c29e420ab333abfd4ba429353e6a6901-p_e.jpg"}]}
{"zpid":"318226197","id":"318226197","rawHomeStatusCd":"ForSale","marketingStatusSimplifiedCd":"For Sale by Agent","imgSrc":"https:\/\/photos.zillowstatic.com\/fp\/9cf2fcb95ed13da350506ae628bdade0-p_e.jpg","hasImage":true,"detailUrl":"https:\/\/www.zillow.com\/homedetails\/50-Liberty-Dr-UNIT-5E-Boston-MA-02210\/318226197_zpid\/","statusType":"FOR_SALE","statusText":"Condo for sale","countryCurrency":"$","price":"$2,895,000","unformattedPrice":2895000,"address":"50 Liberty Dr UNIT 5E, Boston, MA 02210","addressStreet":"50 Liberty Dr UNIT 5E","addressCity":"Boston","addressState":"MA","addressZipcode":"02210","isUndisclosedAddress":false,"beds":1,"baths":2,"area":1297,"latLong":{"latitude":42.35416,"longitude":-71.044525},"isZillowOwned":false,"flexFieldText":"Price cut: $100,000 (Jul 06)","flexFieldType":"priceCut","hdpData":{"homeInfo":{"zpid":318226197,"streetAddress":"50 Liberty Dr UNIT 5E","zipcode":"02210","city":"Boston","state":"MA","latitude":42.35416,"longitude":-71.044525,"price":2895000,"datePriceChanged":1720249200000,"bathrooms":2,"bedrooms":1,"livingArea":1297,"homeType":"CONDO","homeStatus":"FOR_SALE","daysOnZillow":155,"isFeatured":false,"shouldHighlight":false,"zestimate":2729300,"rentZestimate":10053,"listing_sub_type":{"is_FSBA":true},"priceReduction":"$100,000 (Jul 6)","isUnmappable":false,"isPreforeclosureAuction":false,"homeStatusForHDP":"FOR_SALE","priceForHDP":2895000,"priceChange":-100000,"timeOnZillow":13443907000,"isNonOwnerOccupied":true,"isPremierBuilder":false,"isZillowOwned":false,"currency":"USD","country":"USA","taxAssessedValue":2010100,"unit":"Unit 5E","isShowcaseListing":false}},"isSaved":false,"isUserClaimingOwner":false,"isUserConfirmedClaim":false,"pgapt":"ForSale","sgapt":"For Sale (Broker)","zestimate":2729300.0,"shouldShowZestimateAsPrice":false,"has3DModel":false,"hasVideo":false,"isHomeRec":false,"hasAdditionalAttributions":true,"isFeaturedListing":false,"isShowcaseListing":false,"list":true,"relaxed":false,"info6String":"Dalton Spingler","brokerName":"Naples Realty Group","carouselPhotos":[{"url":"https:\/\/photos.zillowstatic.com\/fp\/9cf2fcb95ed13da350506ae628bdade0-p_e.jpg"},{"url":"https:\/\/photos.zillowstatic.com\/fp\/7eae1cf22c262354261090e4117d93f5-p_e.jpg"},{"url":"https:\/\/photos.zillowstatic.com\/fp\/5621dcf37b36223802492e150f2708c7-p_e.jpg"},{"url":"https:\/\/photos.zillowstatic.com\/fp\/db0bb4e18b1c25bdeb5e76091beec70d-p_e.jpg"},{"url":"https:\/\/photos.zillowstatic.com\/fp\/b3f56969d9bcb970f63ee506fb089199-p_e.jpg"},{"url":"https:\/\/photos.zillowstatic.com\/fp\/e0b95a1dbd186a818324a275453fdc26-p_e.jpg"},{"url":"https:\/\/photos.zillowstatic.com\/fp\/4a22768b46427054432f1b0d32ca2f3f-p_e.jpg"},{"url":"https:\/\/photos.zillowstatic.com\/fp\/c597e5f5821c93b970f0fe7f34a48718-p_e.jpg"},{"url":"https:\/\/photos.zillowstatic.com\/fp\/275c80df44b54b1190cd85e2a7db8a0a-p_e.jpg"},{"url":"https:\/\/photos.zillowstatic.com\/fp\/c8abc9bed93c223e1ce556d73dcdca00-p_e.jpg"},{"url":"https:\/\/photos.zillowstatic.com\/fp\/8864a08e16edf549da7627e2ea301c0d-p_e.jpg"},{"url":"https:\/\/photos.zillowstatic.com\/fp\/fdc232a22a87376cc1de40e44633a603-p_e.jpg"},{"url":"https:\/\/photos.zillowstatic.com\/fp\/30abf343d9e4a4b59c8a1e0181fe92cb-p_e.jpg"},{"url":"https:\/\/photos.zillowstatic.com\/fp\/79f390be6ec827239b4423dd0c67af91-p_e.jpg"},{"url":"https:\/\/photos.zillowstatic.com\/fp\/f11e7d63efe00badd7265e2af6eb4d84-p_e.jpg"},{"url":"https:\/\/photos.zillowstatic.com\/fp\/95717d840d66ab8e3331e2f732b27250-p_e.jpg"},{"url":"https:\/\/photos.zillowstatic.com\/fp\/942ad01144d16980fe54e403f33a6619-p_e.jpg"},{"url":"https:\/\/photos.zillowstatic.com\/fp\/1b574fa492d19e442c8f0535e99c5200-p_e.jpg"},{"url":"https:\/\/photos.zillowstatic.com\/fp\/5eb35c30c7ca45718e4de68c27405692-p_e.jpg"},{"url":"https:\/\/photos.zillowstatic.com\/fp\/d634637bf1788c72599c8ed294f31047-p_e.jpg"},{"url":"https:\/\/photos.zillowstatic.com\/fp\/7e31295ab56d5d2268ae27fd33d2fea9-p_e.jpg"},{"url":"https:\/\/photos.zillowstatic.com\/fp\/6ed078d89856a2eff5a920f79036c8c0-p_e.jpg"},{"url":"https:\/\/photos.zillowstatic.com\/fp\/92e2434b286d6686a649d8e8038cf8aa-p_e.jpg"},{"url":"https:\/\/photos.zillowstatic.com\/fp\/5a40fb258d564dcec98cef6d95e676c7-p_e.jpg"},{"url":"https:\/\/photos.zillowstatic.com\/fp\/e5b5bc89494a80758d9bfb5caa6b5dde-p_e.jpg"},{"url":"https:\/\/photos.zillowstatic.com\/fp\/983404954a341570bf27f9a95c1a3dca-p_e.jpg"},{"url":"https:\/\/photos.zillowstatic.com\/fp\/b34089643a9865456627ba565592a322-p_e.jpg"},{"url":"https:\/\/photos.zillowstatic.com\/fp\/e4e83651c4dd51f0adc0af1f41a53eb8-p_e.jpg"},{"url":"https:\/\/photos.zillowstatic.com\/fp\/242db63c5f7417c7001f6f246728b8ad-p_e.jpg"},{"url":"https:\/\/photos.zillowstatic.com\/fp\/5db580c7c0b647b08afc2735eff8e884-p_e.jpg"},{"url":"https:\/\/photos.zillowstatic.com\/fp\/b5e26012b5b9f1ba2dc9fe949b03ad71-p_e.jpg"}]}
{"zpid":"345464122","id":"345464122","rawHomeStatusCd":"ForSale","marketingStatusSimplifiedCd":"For Sale by Agent","imgSrc":"https:\/\/photos.zillowstatic.com\/fp\/446caf4b71a8cbf0589b49a95471569d-p_e.jpg","hasImage":true,"detailUrl":"https:\/\/www.zillow.com\/homedetails\/150-Seaport-Blvd-UNIT-10C-Boston-MA-02210\/345464122_zpid\/","statusType":"FOR_SALE","statusText":"Condo for sale","countryCurrency":"$","price":"$3,049,000","unformattedPrice":3049000,"address":"150 Seaport Blvd UNIT 10C, Boston, MA 02210","addressStreet":"150 Seaport Blvd UNIT 10C","addressCity":"Boston","addressState":"MA","addressZipcode":"02210","isUndisclosedAddress":false,"beds":2,"baths":3,"area":1338,"latLong":{"latitude":42.350754,"longitude":-71.04276},"isZillowOwned":false,"flexFieldText":"121 days on Zillow","flexFieldType":"daysOnZillow","hdpData":{"homeInfo":{"zpid":345464122,"streetAddress":"150 Seaport Blvd UNIT 10C","zipcode":"02210","city":"Boston","state":"MA","latitude":42.350754,"longitude":-71.04276,"price":3049000,"bathrooms":3,"bedrooms":2,"livingArea":1338,"homeType":"CONDO","homeStatus":"FOR_SALE","daysOnZillow":110,"isFeatured":false,"shouldHighlight":false,"listing_sub_type":{"is_FSBA":true},"isUnmappable":false,"isPreforeclosureAuction":false,"homeStatusForHDP":"FOR_SALE","priceForHDP":3049000,"timeOnZillow":9555907000,"isNonOwnerOccupied":true,"isPremierBuilder":false,"isZillowOwned":false,"currency":"USD","country":"USA","unit":"Unit 10C","isShowcaseListing":false}},"isSaved":false,"isUserClaimingOwner":false,"isUserConfirmedClaim":false,"pgapt":"ForSale","sgapt":"For Sale (Broker)","zestimate":null,"shouldShowZestimateAsPrice":false,"has3DModel":false,"hasVideo":false,"isHomeRec":false,"hasAdditionalAttributions":true,"isFeaturedListing":false,"isShowcaseListing":false,"list":true,"relaxed":false,"info6String":"Michael Moynihan","brokerName":"TCC \/ St. Regis Residences","carouselPhotos":[{"url":"https:\/\/photos.zillowstatic.com\/fp\/446caf4b71a8cbf0589b49a95471569d-p_e.jpg"},{"url":"https:\/\/photos.zillowstatic.com\/fp\/fd21063e64528502b72de65ab1300fa1-p_e.jpg"},{"url":"https:\/\/photos.zillowstatic.com\/fp\/887f65381c0ed6237f64bc0a32885398-p_e.jpg"},{"url":"https:\/\/photos.zillowstatic.com\/fp\/bd83b4326fa244b884be394d59c45a83-p_e.jpg"},{"url":"https:\/\/photos.zillowstatic.com\/fp\/22cdcf10f58833380e08afc3873158a8-p_e.jpg"},{"url":"https:\/\/photos.zillowstatic.com\/fp\/e1b482be2ab67550b8fdeeb6312ef117-p_e.jpg"},{"url":"https:\/\/photos.zillowstatic.com\/fp\/81b2781e72e61468f9434bb47da0a3b2-p_e.jpg"},{"url":"https:\/\/photos.zillowstatic.com\/fp\/e7b84f8d0b290c77c392625c4fd063c3-p_e.jpg"},{"url":"https:\/\/photos.zillowstatic.com\/fp\/0149cf3667243be10e60a21b7b2a7e9e-p_e.jpg"},{"url":"https:\/\/photos.zillowstatic.com\/fp\/4072b249d7e6d1165ec107e796ce3578-p_e.jpg"},{"url":"https:\/\/photos.zillowstatic.com\/fp\/f8b0a736ab6739a0012eac38a0fa8d9a-p_e.jpg"},{"url":"https:\/\/photos.zillowstatic.com\/fp\/5fb87265c9dbcb27291e5cb5a3d1933e-p_e.jpg"},{"url":"https:\/\/photos.zillowstatic.com\/fp\/c719567e6bb2ac4880485cc1528faa51-p_e.jpg"},{"url":"https:\/\/photos.zillowstatic.com\/fp\/5839e349dbab1ab1226e3a7a8ef5ed67-p_e.jpg"},{"url":"https:\/\/photos.zillowstatic.com\/fp\/ccaadc92868fdc08ea665c3af8c7691a-p_e.jpg"},{"url":"https:\/\/photos.zillowstatic.com\/fp\/5e6171e8adfc8f89c572182188cf9ba3-p_e.jpg"},{"url":"https:\/\/photos.zillowstatic.com\/fp\/9e09cd3d5e008f5f44f0dda94c74b093-p_e.jpg"},{"url":"https:\/\/photos.zillowstatic.com\/fp\/65fb78ef6be8f7fc0bd1636cfe61f9ad-p_e.jpg"},{"url":"https:\/\/photos.zillowstatic.com\/fp\/f590a4837d33307412bac4f7bf857e7d-p_e.jpg"},{"url":"https:\/\/photos.zillowstatic.com\/fp\/53f15a7e88248f5972854c6a050ccff5-p_e.jpg"},{"url":"https:\/\/photos.zillowstatic.com\/fp\/d66e6cace78f3c6beaab195409849eab-p_e.jpg"},{"url":"https:\/\/photos.zillowstatic.com\/fp\/f4996b9fb88f8761197aa679c42fc8b3-p_e.jpg"},{"url":"https:\/\/photos.zillowstatic.com\/fp\/c37873aa949f2c5f8255e9d85f73aff5-p_e.jpg"},{"url":"https:\/\/photos.zillowstatic.com\/fp\/53df807acfbeea04467bbc308c91738c-p_e.jpg"},{"url":"https:\/\/photos.zillowstatic.com\/fp\/3ce684b4313cd30ca8c335fd129ff88a-p_e.jpg"},{"url":"https:\/\/photos.zillowstatic.com\/fp\/17e978eecca654fd0d8ff620f48956e2-p_e.jpg"}]}
{"zpid":"239893116","id":"239893116","rawHomeStatusCd":"ForSale","marketingStatusSimplifiedCd":"For Sale by Agent","imgSrc":"https:\/\/photos.zillowstatic.com\/fp\/491b0bdcc4012a7566491bfc4934a663-p_e.jpg","hasImage":true,"detailUrl":"https:\/\/www.zillow.com\/homedetails\/22-Liberty-Dr-UNIT-7F-Boston-MA-02210\/239893116_zpid\/","statusType":"FOR_SALE","statusText":"Condo for sale","countryCurrency":"$","price":"$5,395,000","unformattedPrice":5395000,"address":"22 Liberty Dr UNIT 7F, Boston, MA 02210","addressStreet":"22 Liberty Dr UNIT 7F","addressCity":"Boston","addressState":"MA","addressZipcode":"02210","isUndisclosedAddress":false,"beds":2,"baths":3,"area":1859,"latLong":{"latitude":42.354733,"longitude":-71.04565},"isZillowOwned":false,"flexFieldText":"33 days on Zillow","flexFieldType":"daysOnZillow","hdpData":{"homeInfo":{"zpid":239893116,"streetAddress":"22 Liberty Dr UNIT 7F","zipcode":"02210","city":"Boston","state":"MA","latitude":42.354733,"longitude":-71.04565,"price":5395000,"bathrooms":3,"bedrooms":2,"livingArea":1859,"homeType":"CONDO","homeStatus":"FOR_SALE","daysOnZillow":34,"isFeatured":false,"shouldHighlight":false,"zestimate":5154400,"rentZestimate":21776,"listing_sub_type":{"is_FSBA":true},"isUnmappable":false,"isPreforeclosureAuction":false,"homeStatusForHDP":"FOR_SALE","priceForHDP":5395000,"timeOnZillow":2989507000,"isNonOwnerOccupied":true,"isPremierBuilder":false,"isZillowOwned":false,"currency":"USD","country":"USA","taxAssessedValue":4335000,"unit":"Unit 7F","isShowcaseListing":false}},"isSaved":false,"isUserClaimingOwner":false,"isUserConfirmedClaim":false,"pgapt":"ForSale","sgapt":"For Sale (Broker)","zestimate":5154400.0,"shouldShowZestimateAsPrice":false,"has3DModel":false,"hasVideo":false,"isHomeRec":false,"hasAdditionalAttributions":true,"isFeaturedListing":false,"isShowcaseListing":false,"list":true,"relaxed":false,"info6String":"Taylor Blacker","brokerName":"Luxury Residential Group, LLC","carouselPhotos":[{"url":"https:\/\/photos.zillowstatic.com\/fp\/491b0bdcc4012a7566491bfc4934a663-p_e.jpg"},{"url":"https:\/\/photos.zillowstatic.com\/fp\/a15f89718408824293ab69a0e4a45c4d-p_e.jpg"},{"url":"https:\/\/photos.zillowstatic.com\/fp\/189991a6fcc9921ffbec91fe27747cbe-p_e.jpg"},{"url":"https:\/\/photos.zillowstatic.com\/fp\/880d3c254f74bda657dba11461b0abe7-p_e.jpg"},{"url":"https:\/\/photos.zillowstatic.com\/fp\/47013527364ebd4d29ae204d1ed0617d-p_e.jpg"},{"url":"https:\/\/photos.zillowstatic.com\/fp\/0f027e5fb10bcaf4a04d2036cbd138ad-p_e.jpg"},{"url":"https:\/\/photos.zillowstatic.com\/fp\/ff3db0c7c9c7417db1a703628b0ae95f-p_e.jpg"},{"url":"https:\/\/photos.zillowstatic.com\/fp\/10e9853e83d8db09e11e62af8d5eadc2-p_e.jpg"},{"url":"https:\/\/photos.zillowstatic.com\/fp\/3a5ad4f5c6ff66bc71dff339567edf83-p_e.jpg"},{"url":"https:\/\/photos.zillowstatic.com\/fp\/547a87380404f0b3228df0866f58c50e-p_e.jpg"},{"url":"https:\/\/photos.zillowstatic.com\/fp\/c2717e412b5e1369abe32d172f39fef7-p_e.jpg"},{"url":"https:\/\/photos.zillowstatic.com\/fp\/6ca72bf41933cb1929659426e45410c3-p_e.jpg"},{"url":"https:\/\/photos.zillowstatic.com\/fp\/0494198b3d579121205fce1ffc9ca7cf-p_e.jpg"},{"url":"https:\/\/photos.zillowstatic.com\/fp\/bf7f5b68fa5d10f140ae92f15365776e-p_e.jpg"},{"url":"https:\/\/photos.zillowstatic.com\/fp\/08fc7e29af4bc315cfbdb3b3818baf34-p_e.jpg"},{"url":"https:\/\/photos.zillowstatic.com\/fp\/664f1a42f6f200e8d3376456cbf63bb2-p_e.jpg"},{"url":"https:\/\/photos.zillowstatic.com\/fp\/aacb4ec433e21620a7a7e34ef09a094a-p_e.jpg"},{"url":"https:\/\/photos.zillowstatic.com\/fp\/727f38c1d495152708e7dbbd2eabce9a-p_e.jpg"},{"url":"https:\/\/photos.zillowstatic.com\/fp\/9cae79672e82bb7e0b3e717d96ece824-p_e.jpg"},{"url":"https:\/\/photos.zillowstatic.com\/fp\/29c1763c0990c191e4ea872284186f3f-p_e.jpg"},{"url":"https:\/\/photos.zillowstatic.com\/fp\/1446c951aad15bfee3bdd43ed2a925b8-p_e.jpg"},{"url":"https:\/\/photos.zillowstatic.com\/fp\/e7936643c593f549c71b3c93a9cc9a39-p_e.jpg"},{"url":"https:\/\/photos.zillowstatic.com\/fp\/b66d8946ab029f2cba8885912163074a-p_e.jpg"},{"url":"https:\/\/photos.zillowstatic.com\/fp\/b7467f8c5fe258cbebb27fcd7bc42162-p_e.jpg"},{"url":"https:\/\/photos.zillowstatic.com\/fp\/ceff7034dd79db010537a070d32fea91-p_e.jpg"},{"url":"https:\/\/photos.zillowstatic.com\/fp\/edab9a6ebfd652e1f1f64dc9f12ac0be-p_e.jpg"},{"url":"https:\/\/photos.zillowstatic.com\/fp\/20a91b7567c554baaecd5192fcb67a53-p_e.jpg"},{"url":"https:\/\/photos.zillowstatic.com\/fp\/ed7f776c594e46b163c01f335a67af81-p_e.jpg"},{"url":"https:\/\/photos.zillowstatic.com\/fp\/39b53c073af95a053b4c97bccc2db25f-p_e.jpg"}]}
{"zpid":"81857453","id":"81857453","rawHomeStatusCd":"ForSale","marketingStatusSimplifiedCd":"For Sale by Agent","imgSrc":"https:\/\/photos.zillowstatic.com\/fp\/522ff0bbdb63efc70d5f4720e1d716e6-p_e.jpg","hasImage":true,"detailUrl":"https:\/\/www.zillow.com\/homedetails\/500-Atlantic-Ave-UNIT-17K-Boston-MA-02210\/81857453_zpid\/","statusType":"FOR_SALE","statusText":"Condo for sale","countryCurrency":"$","price":"$4,500,000","unformattedPrice":4500000,"address":"500 Atlantic Ave UNIT 17K, Boston, MA 02210","addressStreet":"500 Atlantic Ave UNIT 17K","addressCity":"Boston","addressState":"MA","addressZipcode":"02210","isUndisclosedAddress":false,"beds":3,"baths":5,"area":3385,"latLong":{"latitude":42.353855,"longitude":-71.052},"isZillowOwned":false,"flexFieldText":"324 days on Zillow","flexFieldType":"daysOnZillow","hdpData":{"homeInfo":{"zpid":81857453,"streetAddress":"500 Atlantic Ave UNIT 17K","zipcode":"02210","city":"Boston","state":"MA","latitude":42.353855,"longitude":-71.052,"price":4500000,"datePriceChanged":1714978800000,"bathrooms":5,"bedrooms":3,"livingArea":3385,"homeType":"CONDO","homeStatus":"FOR_SALE","daysOnZillow":318,"isFeatured":false,"shouldHighlight":false,"zestimate":4172700,"rentZestimate":17123,"listing_sub_type":{"is_FSBA":true},"priceReduction":"$230,000 (May 6)","isUnmappable":false,"isPreforeclosureAuction":false,"homeStatusForHDP":"FOR_SALE","priceForHDP":4500000,"priceChange":-230000,"timeOnZillow":27527107000,"isNonOwnerOccupied":true,"isPremierBuilder":false,"isZillowOwned":false,"currency":"USD","country":"USA","taxAssessedValue":3633300,"unit":"Unit 17K","isShowcaseListing":false}},"isSaved":false,"isUserClaimingOwner":false,"isUserConfirmedClaim":false,"pgapt":"ForSale","sgapt":"For Sale (Broker)","zestimate":4172700.0,"shouldShowZestimateAsPrice":false,"has3DModel":false,"hasVideo":false,"isHomeRec":false,"hasAdditionalAttributions":true,"isFeaturedListing":false,"isShowcaseListing":false,"list":true,"relaxed":false,"info6String":"Cheryl & Tim Marsh","brokerName":"Marsh Properties, Inc.","carouselPhotos":[{"url":"https:\/\/photos.zillowstatic.com\/fp\/522ff0bbdb63efc70d5f4720e1d716e6-p_e.jpg"},{"url":"https:\/\/photos.zillowstatic.com\/fp\/2ca5eb88c1f2f8194ded0db712427b20-p_e.jpg"},{"url":"https:\/\/photos.zillowstatic.com\/fp\/5c96a55cfc735eb1d6bea5ed8333e2b5-p_e.jpg"},{"url":"https:\/\/photos.zillowstatic.com\/fp\/13ab4f57b0f2efdc2e9b874a02285a3c-p_e.jpg"},{"url":"https:\/\/photos.zillowstatic.com\/fp\/c308fe2b500e986fde32eb007916cb2b-p_e.jpg"},{"url":"https:\/\/photos.zillowstatic.com\/fp\/df4b9f5141ee6ee4abd0f43ca1acadd4-p_e.jpg"},{"url":"https:\/\/photos.zillowstatic.com\/fp\/fc1918e806ab93dd748ee5694922ee08-p_e.jpg"},{"url":"https:\/\/photos.zillowstatic.com\/fp\/f96ecf72f4a0e720e0ebf5fc619803a9-p_e.jpg"},{"url":"https:\/\/photos.zillowstatic.com\/fp\/a744ccc7ecb76957b6f9121bcbf855ab-p_e.jpg"},{"url":"https:\/\/photos.zillowstatic.com\/fp\/021074949dbb2646faf231455e426480-p_e.jpg"},{"url":"https:\/\/photos.zillowstatic.com\/fp\/83eb47e7003cc3bd35911a7b7371eaa0-p_e.jpg"},{"url":"https:\/\/photos.zillowstatic.com\/fp\/e0cd8c686f2b81e105e81e9e18453e93-p_e.jpg"},{"url":"https:\/\/photos.zillowstatic.com\/fp\/3f59f6a92ea10076e9e4f0a8e0ca9a67-p_e.jpg"},{"url":"https:\/\/photos.zillowstatic.com\/fp\/1df4b0be980fc421fde49e1886c88ff3-p_e.jpg"},{"url":"https:\/\/photos.zillowstatic.com\/fp\/1b33deaa477649424bd2dc9dc24e59c1-p_e.jpg"},{"url":"https:\/\/photos.zillowstatic.com\/fp\/3d91d62f5c8bef2240a122699f3be489-p_e.jpg"},{"url":"https:\/\/photos.zillowstatic.com\/fp\/969e439f4550e5c8286ba419ff7d7431-p_e.jpg"},{"url":"https:\/\/photos.zillowstatic.com\/fp\/a3bd1307a87f4ea4c83019735f94c844-p_e.jpg"},{"url":"https:\/\/photos.zillowstatic.com\/fp\/b7cd00635d5ac836b040194c60a0bca3-p_e.jpg"},{"url":"https:\/\/photos.zillowstatic.com\/fp\/7daf2c5eed46cd297bdf5b1d7f669c98-p_e.jpg"},{"url":"https:\/\/photos.zillowstatic.com\/fp\/cdab757db48dfb5b28d98b16931aa2c7-p_e.jpg"},{"url":"https:\/\/photos.zillowstatic.com\/fp\/2d6fc77bfd17c5fae5f5c6f0d756e762-p_e.jpg"},{"url":"https:\/\/photos.zillowstatic.com\/fp\/98f2c40f7f7b9e6bc3648f2af76f3ace-p_e.jpg"},{"url":"https:\/\/photos.zillowstatic.com\/fp\/774604fd5fbaf22c9fd9696534d9f946-p_e.jpg"},{"url":"https:\/\/photos.zillowstatic.com\/fp\/b4b96c10a5bde7f4bb0ad42cd1502922-p_e.jpg"},{"url":"https:\/\/photos.zillowstatic.com\/fp\/4274d27de2224730e3d87e1370e30e14-p_e.jpg"},{"url":"https:\/\/photos.zillowstatic.com\/fp\/5503a6decc3ff7d8768a1adb2af338e8-p_e.jpg"},{"url":"https:\/\/photos.zillowstatic.com\/fp\/68b7d5ba74b3deafd97ca0211320e383-p_e.jpg"},{"url":"https:\/\/photos.zillowstatic.com\/fp\/1e7d1bd772260c4c54834e9496348f21-p_e.jpg"},{"url":"https:\/\/photos.zillowstatic.com\/fp\/b9ba8c78148bc2b5224eb222492d9fa5-p_e.jpg"},{"url":"https:\/\/photos.zillowstatic.com\/fp\/cc2a926a023cf90769603b76247136b0-p_e.jpg"},{"url":"https:\/\/photos.zillowstatic.com\/fp\/9145a265ea622c37c909f778e05bb86e-p_e.jpg"},{"url":"https:\/\/photos.zillowstatic.com\/fp\/40a6b693d23220e33aa4426f6f575927-p_e.jpg"}]}
{"zpid":"2057896645","id":"2057896645","rawHomeStatusCd":"ForSale","marketingStatusSimplifiedCd":"For Sale by Agent","imgSrc":"https:\/\/photos.zillowstatic.com\/fp\/dad3fd7e8a2eec855ac2eabec1a641a3-p_e.jpg","hasImage":true,"detailUrl":"https:\/\/www.zillow.com\/homedetails\/150-Seaport-Blvd-UNIT-5F-Boston-MA-02210\/2057896645_zpid\/","statusType":"FOR_SALE","statusText":"Condo for sale","countryCurrency":"$","price":"$1,849,000","unformattedPrice":1849000,"address":"150 Seaport Blvd UNIT 5F, Boston, MA 02210","addressStreet":"150 Seaport Blvd UNIT 5F","addressCity":"Boston","addressState":"MA","addressZipcode":"02210","isUndisclosedAddress":false,"beds":1,"baths":1,"area":924,"latLong":{"latitude":42.350754,"longitude":-71.04276},"isZillowOwned":false,"flexFieldText":"149 days on Zillow","flexFieldType":"daysOnZillow","hdpData":{"homeInfo":{"zpid":2057896645,"streetAddress":"150 Seaport Blvd UNIT 5F","zipcode":"02210","city":"Boston","state":"MA","latitude":42.350754,"longitude":-71.04276,"price":1849000,"datePriceChanged":1711436400000,"bathrooms":1,"bedrooms":1,"livingArea":924,"homeType":"CONDO","homeStatus":"FOR_SALE","daysOnZillow":150,"isFeatured":false,"shouldHighlight":false,"zestimate":1760300,"rentZestimate":7122,"listing_sub_type":{"is_FSBA":true},"priceReduction":"","isUnmappable":false,"isPreforeclosureAuction":false,"homeStatusForHDP":"FOR_SALE","priceForHDP":1849000,"priceChange":-186000,"timeOnZillow":13011907000,"isNonOwnerOccupied":true,"isPremierBuilder":false,"isZillowOwned":false,"currency":"USD","country":"USA","unit":"Unit 5F","lotAreaValue":0,"lotAreaUnit":"sqft","isShowcaseListing":false}},"isSaved":false,"isUserClaimingOwner":false,"isUserConfirmedClaim":false,"pgapt":"ForSale","sgapt":"For Sale (Broker)","zestimate":1760300.0,"shouldShowZestimateAsPrice":false,"has3DModel":false,"hasVideo":false,"isHomeRec":false,"hasAdditionalAttributions":false,"isFeaturedListing":false,"isShowcaseListing":false,"list":true,"relaxed":false,"info6String":null,"brokerName":null,"carouselPhotos":[{"url":"https:\/\/photos.zillowstatic.com\/fp\/dad3fd7e8a2eec855ac2eabec1a641a3-p_e.jpg"},{"url":"https:\/\/photos.zillowstatic.com\/fp\/1185d3c4d9d05f3c0710428a1bf7a5e2-p_e.jpg"},{"url":"https:\/\/photos.zillowstatic.com\/fp\/6ee139f2b6d5316bc2099e0dc4447da0-p_e.jpg"},{"url":"https:\/\/photos.zillowstatic.com\/fp\/8eec095d65d8dfa58743a380405e83c3-p_e.jpg"},{"url":"https:\/\/photos.zillowstatic.com\/fp\/e57935e08ba5cd4afe3e19b1f626285d-p_e.jpg"},{"url":"https:\/\/photos.zillowstatic.com\/fp\/30aa84a42b3648149f6051d8294d6b88-p_e.jpg"},{"url":"https:\/\/photos.zillowstatic.com\/fp\/83f0e93ab09c587c04abae0013381f84-p_e.jpg"},{"url":"https:\/\/photos.zillowstatic.com\/fp\/2770b168f1f6901a0c1a5b5acc826ff3-p_e.jpg"},{"url":"https:\/\/photos.zillowstatic.com\/fp\/fd5073d5f01832a17957a2917fecf38d-p_e.jpg"},{"url":"https:\/\/photos.zillowstatic.com\/fp\/913735361a4815c379290c9c79116d08-p_e.jpg"},{"url":"https:\/\/photos.zillowstatic.com\/fp\/ed88a5045efca5a1a492f16cabe78902-p_e.jpg"},{"url":"https:\/\/photos.zillowstatic.com\/fp\/99b8402fe12c18412abf6db1969dd072-p_e.jpg"},{"url":"https:\/\/photos.zillowstatic.com\/fp\/f29d617916c3d83235d031acff7df660-p_e.jpg"},{"url":"https:\/\/photos.zillowstatic.com\/fp\/7f8889745e2d827521c3f179bcbff5c8-p_e.jpg"},{"url":"https:\/\/photos.zillowstatic.com\/fp\/3c03d118dc2ab62f5ac2cfe13328ad22-p_e.jpg"},{"url":"https:\/\/photos.zillowstatic.com\/fp\/efe2b033835138f261fc0992309ab515-p_e.jpg"},{"url":"https:\/\/photos.zillowstatic.com\/fp\/b0e1a571a4394e38d35988b564fd33b8-p_e.jpg"},{"url":"https:\/\/photos.zillowstatic.com\/fp\/e4dfea64d1a95e670bc52f434505584b-p_e.jpg"},{"url":"https:\/\/photos.zillowstatic.com\/fp\/f25586495921ff104b83af1feb68c471-p_e.jpg"},{"url":"https:\/\/photos.zillowstatic.com\/fp\/35b2c0272bfe88a0c21e4b821ab174ac-p_e.jpg"},{"url":"https:\/\/photos.zillowstatic.com\/fp\/ef78d1c19f4b1c6ad0719a23526e4a42-p_e.jpg"},{"url":"https:\/\/photos.zillowstatic.com\/fp\/8cdf3ddd4de605a61b4b53f33b7bde63-p_e.jpg"},{"url":"https:\/\/photos.zillowstatic.com\/fp\/166eb5f84d68b9306d88ebe03c8efe41-p_e.jpg"},{"url":"https:\/\/photos.zillowstatic.com\/fp\/6f5b1ca511bb7ab7115e676a68eb3e5a-p_e.jpg"},{"url":"https:\/\/photos.zillowstatic.com\/fp\/ee4ad70effa74cb5a2793cea7ae92cfd-p_e.jpg"},{"url":"https:\/\/photos.zillowstatic.com\/fp\/104225c92566a7a753f3107b14472243-p_e.jpg"},{"url":"https:\/\/photos.zillowstatic.com\/fp\/10fa759294cfa4f35904fe876a0f0e8c-p_e.jpg"},{"url":"https:\/\/photos.zillowstatic.com\/fp\/536c0c138f1fb477ce036dd2d578b973-p_e.jpg"},{"url":"https:\/\/photos.zillowstatic.com\/fp\/2c80903b62ce20878eb0a9f077b6cf73-p_e.jpg"}]}
{"zpid":"333605967","id":"333605967","rawHomeStatusCd":"ForSale","marketingStatusSimplifiedCd":"For Sale by Agent","imgSrc":"https:\/\/photos.zillowstatic.com\/fp\/c8cf18b776a9baed01feb802c321fc07-p_e.jpg","hasImage":true,"detailUrl":"https:\/\/www.zillow.com\/homedetails\/133-Seaport-Blvd-UNIT-620-Boston-MA-02210\/333605967_zpid\/","statusType":"FOR_SALE","statusText":"Condo for sale","countryCurrency":"$","price":"$2,199,900","unformattedPrice":2199900,"address":"133 Seaport Blvd UNIT 620, Boston, MA 02210","addressStreet":"133 Seaport Blvd UNIT 620","addressCity":"Boston","addressState":"MA","addressZipcode":"02210","isUndisclosedAddress":false,"beds":2,"baths":3,"area":1255,"latLong":{"latitude":42.35051,"longitude":-71.04362},"isZillowOwned":false,"flexFieldText":"303 days on Zillow","flexFieldType":"daysOnZillow","hdpData":{"homeInfo":{"zpid":333605967,"streetAddress":"133 Seaport Blvd UNIT 620","zipcode":"02210","city":"Boston","state":"MA","latitude":42.35051,"longitude":-71.04362,"price":2199900,"datePriceChanged":1718607600000,"bathrooms":3,"bedrooms":2,"livingArea":1255,"homeType":"CONDO","homeStatus":"FOR_SALE","daysOnZillow":304,"isFeatured":false,"shouldHighlight":false,"zestimate":2083300,"rentZestimate":8343,"listing_sub_type":{"is_FSBA":true},"priceReduction":"$49,100 (Jun 17)","isUnmappable":false,"isPreforeclosureAuction":false,"homeStatusForHDP":"FOR_SALE","priceForHDP":2199900,"priceChange":-49100,"timeOnZillow":26317507000,"isNonOwnerOccupied":true,"isPremierBuilder":false,"isZillowOwned":false,"currency":"USD","country":"USA","taxAssessedValue":1888000,"unit":"Unit 620","isShowcaseListing":false}},"isSaved":false,"isUserClaimingOwner":false,"isUserConfirmedClaim":false,"pgapt":"ForSale","sgapt":"For Sale (Broker)","zestimate":2083300.0,"shouldShowZestimateAsPrice":false,"has3DModel":false,"hasVideo":false,"isHomeRec":false,"hasAdditionalAttributions":true,"isFeaturedListing":false,"isShowcaseListing":false,"list":true,"relaxed":false,"info6String":"Derrick Goldsmith","brokerName":"Sold By Gold LLC","carouselPhotos":[{"url":"https:\/\/photos.zillowstatic.com\/fp\/c8cf18b776a9baed01feb802c321fc07-p_e.jpg"},{"url":"https:\/\/photos.zillowstatic.com\/fp\/5b7686b303df88d827a02fb3df3239e3-p_e.jpg"},{"url":"https:\/\/photos.zillowstatic.com\/fp\/9316096c35d1f7d8ee2116b9efe6013e-p_e.jpg"},{"url":"https:\/\/photos.zillowstatic.com\/fp\/bbb82fdf76821b7fb1ed1559205ffd4e-p_e.jpg"},{"url":"https:\/\/photos.zillowstatic.com\/fp\/38785645d8c8d477343fbca460e91c2f-p_e.jpg"},{"url":"https:\/\/photos.zillowstatic.com\/fp\/22e56a8a4c940a2d230ab66544eca20f-p_e.jpg"},{"url":"https:\/\/photos.zillowstatic.com\/fp\/6f3c30a7365cd33292ba9c4cf92e8f25-p_e.jpg"},{"url":"https:\/\/photos.zillowstatic.com\/fp\/38661bbd815a2cc009c25e7cf4a52562-p_e.jpg"},{"url":"https:\/\/photos.zillowstatic.com\/fp\/ffaf6a77970d9499d40e39d228af4552-p_e.jpg"},{"url":"https:\/\/photos.zillowstatic.com\/fp\/27a669f4c0dae6f2927259b5307c3414-p_e.jpg"},{"url":"https:\/\/photos.zillowstatic.com\/fp\/11890fcbedd598d74e75de273424092f-p_e.jpg"},{"url":"https:\/\/photos.zillowstatic.com\/fp\/98ac36ff5cd729f8490ed9eaa20ea97c-p_e.jpg"},{"url":"https:\/\/photos.zillowstatic.com\/fp\/c3fbec71cf82af03d712c5c2eff88ee6-p_e.jpg"},{"url":"https:\/\/photos.zillowstatic.com\/fp\/dc70defa309a65a8a1ea75edd99717b1-p_e.jpg"},{"url":"https:\/\/photos.zillowstatic.com\/fp\/ab9a00ecfd1034f28d62a0302b04e7f6-p_e.jpg"},{"url":"https:\/\/photos.zillowstatic.com\/fp\/75e0b1e5319417267d366858da492ed0-p_e.jpg"},{"url":"https:\/\/photos.zillowstatic.com\/fp\/5a34d2c4e04962ada16a89987759bac1-p_e.jpg"},{"url":"https:\/\/photos.zillowstatic.com\/fp\/31b94c1e7d53f6a490da377d8a5b0412-p_e.jpg"},{"url":"https:\/\/photos.zillowstatic.com\/fp\/7fd0bb314ddccb6208d100a8f58edb0b-p_e.jpg"},{"url":"https:\/\/photos.zillowstatic.com\/fp\/5087a415efee9386db4644f26ef9c86b-p_e.jpg"},{"url":"https:\/\/photos.zillowstatic.com\/fp\/1d19b1520764663d89bd5fdeae68356f-p_e.jpg"},{"url":"https:\/\/photos.zillowstatic.com\/fp\/7749f96ca3a3702e8b02b9054ca71bb5-p_e.jpg"},{"url":"https:\/\/photos.zillowstatic.com\/fp\/9aaa89080c1212ebadb3f6f8c8b63ab8-p_e.jpg"},{"url":"https:\/\/photos.zillowstatic.com\/fp\/dc81f0377c42dfac582c8484be77081a-p_e.jpg"},{"url":"https:\/\/photos.zillowstatic.com\/fp\/7e97f9d8d9da9eaada414867aa9fc2dd-p_e.jpg"},{"url":"https:\/\/photos.zillowstatic.com\/fp\/ffac5f77d3f05c881b6c51621dc992f3-p_e.jpg"},{"url":"https:\/\/photos.zillowstatic.com\/fp\/39d24dd74357f27d89f2bf856ab7c265-p_e.jpg"},{"url":"https:\/\/photos.zillowstatic.com\/fp\/aba2ac09598dceee24de0786875d02ff-p_e.jpg"},{"url":"https:\/\/photos.zillowstatic.com\/fp\/434a0eef8f3a520b7f0305863529fce1-p_e.jpg"},{"url":"https:\/\/photos.zillowstatic.com\/fp\/12a960ebcde346c07d638fa46d5e9bd3-p_e.jpg"},{"url":"https:\/\/photos.zillowstatic.com\/fp\/cd8f2a13e4a57e3f1e50eea424f69619-p_e.jpg"},{"url":"https:\/\/photos.zillowstatic.com\/fp\/2f9a4fa09b03c594dd5fd904d3cc2df8-p_e.jpg"},{"url":"https:\/\/photos.zillowstatic.com\/fp\/38584d2591183075b494b3acfc16abd2-p_e.jpg"},{"url":"https:\/\/photos.zillowstatic.com\/fp\/939b3d0fc608fd2342a91f783f6ff9b8-p_e.jpg"},{"url":"https:\/\/photos.zillowstatic.com\/fp\/9422fd1d87bcde252bcf9a94b03bc733-p_e.jpg"},{"url":"https:\/\/photos.zillowstatic.com\/fp\/f91b58b00ce497876f0fbe3fc3609205-p_e.jpg"},{"url":"https:\/\/photos.zillowstatic.com\/fp\/21073e2a5e633e8f7140acbd2ec2805f-p_e.jpg"},{"url":"https:\/\/photos.zillowstatic.com\/fp\/651e3821faa5374123bc862c6f434315-p_e.jpg"},{"url":"https:\/\/photos.zillowstatic.com\/fp\/d8fe2a48cfa80d3e73ba70d3c1b05d6d-p_e.jpg"},{"url":"https:\/\/photos.zillowstatic.com\/fp\/9066b3d13ae432cb5be01ffbb389bd1a-p_e.jpg"},{"url":"https:\/\/photos.zillowstatic.com\/fp\/e35845c547087a9bcfb11873f3d2cdfa-p_e.jpg"},{"url":"https:\/\/photos.zillowstatic.com\/fp\/9aeabd88fabbca7f080076ccba230aa2-p_e.jpg"}]}
{"zpid":"81858000","id":"81858000","rawHomeStatusCd":"ForSale","marketingStatusSimplifiedCd":"For Sale by Agent","imgSrc":"https:\/\/photos.zillowstatic.com\/fp\/a6e2c8dba222635f0e0f64cf1e645f34-p_e.jpg","hasImage":true,"detailUrl":"https:\/\/www.zillow.com\/homedetails\/500-Atlantic-Ave-UNIT-17M-Boston-MA-02210\/81858000_zpid\/","statusType":"FOR_SALE","statusText":"Condo for sale","countryCurrency":"$","price":"$1,795,000","unformattedPrice":1795000,"address":"500 Atlantic Ave UNIT 17M, Boston, MA 02210","addressStreet":"500 Atlantic Ave UNIT 17M","addressCity":"Boston","addressState":"MA","addressZipcode":"02210","isUndisclosedAddress":false,"beds":2,"baths":3,"area":1483,"latLong":{"latitude":42.354042,"longitude":-71.05218},"isZillowOwned":false,"flexFieldText":"30 days on Zillow","flexFieldType":"daysOnZillow","hdpData":{"homeInfo":{"zpid":81858000,"streetAddress":"500 Atlantic Ave UNIT 17M","zipcode":"02210","city":"Boston","state":"MA","latitude":42.354042,"longitude":-71.05218,"price":1795000,"bathrooms":3,"bedrooms":2,"livingArea":1483,"homeType":"CONDO","homeStatus":"FOR_SALE","daysOnZillow":31,"isFeatured":false,"shouldHighlight":false,"zestimate":1744200,"rentZestimate":7366,"listing_sub_type":{"is_FSBA":true},"isUnmappable":false,"isPreforeclosureAuction":false,"homeStatusForHDP":"FOR_SALE","priceForHDP":1795000,"timeOnZillow":2730307000,"isNonOwnerOccupied":true,"isPremierBuilder":false,"isZillowOwned":false,"currency":"USD","country":"USA","taxAssessedValue":1773200,"unit":"Unit 17M","lotAreaValue":1483,"lotAreaUnit":"sqft","isShowcaseListing":false}},"isSaved":false,"isUserClaimingOwner":false,"isUserConfirmedClaim":false,"pgapt":"ForSale","sgapt":"For Sale (Broker)","zestimate":1744200.0,"shouldShowZestimateAsPrice":false,"has3DModel":false,"hasVideo":false,"isHomeRec":false,"hasAdditionalAttributions":true,"isFeaturedListing":false,"isShowcaseListing":false,"list":true,"relaxed":false,"info6String":"Marcus Rashotsky","brokerName":"Linnane Real Estate","carouselPhotos":[{"url":"https:\/\/photos.zillowstatic.com\/fp\/a6e2c8dba222635f0e0f64cf1e645f34-p_e.jpg"},{"url":"https:\/\/photos.zillowstatic.com\/fp\/ca2002cbbb48e5315a84f6509e7600c5-p_e.jpg"},{"url":"https:\/\/photos.zillowstatic.com\/fp\/1927b36528527a85c2d1e825c7256e4a-p_e.jpg"},{"url":"https:\/\/photos.zillowstatic.com\/fp\/80a691d7e72c2491bccd2457a6331e57-p_e.jpg"},{"url":"https:\/\/photos.zillowstatic.com\/fp\/16ac88439b1b79b146d0807cc80a6e38-p_e.jpg"},{"url":"https:\/\/photos.zillowstatic.com\/fp\/25fbc70d489d955dfffed05563875b61-p_e.jpg"},{"url":"https:\/\/photos.zillowstatic.com\/fp\/5b97fff3f48fc0ce95e74a03c1c0b165-p_e.jpg"},{"url":"https:\/\/photos.zillowstatic.com\/fp\/f2737576eda19c686d8d423ac42815aa-p_e.jpg"},{"url":"https:\/\/photos.zillowstatic.com\/fp\/908b8aa79add682043f70d2c4880e285-p_e.jpg"}]}
{"zpid":"2055520175","id":"2055520175","rawHomeStatusCd":"ForSale","marketingStatusSimplifiedCd":"For Sale by Agent","imgSrc":"https:\/\/photos.zillowstatic.com\/fp\/b900fb776103f539bce3970880772889-p_e.jpg","hasImage":true,"detailUrl":"https:\/\/www.zillow.com\/homedetails\/150-Seaport-Blvd-5A-Boston-MA-02210\/2055520175_zpid\/","statusType":"FOR_SALE","statusText":"Condo for sale","countryCurrency":"$","price":"$2,100,000","unformattedPrice":2100000,"address":"150 Seaport Blvd #5A, Boston, MA 02210","addressStreet":"150 Seaport Blvd #5A","addressCity":"Boston","addressState":"MA","addressZipcode":"02210","isUndisclosedAddress":false,"beds":1,"baths":2,"area":996,"latLong":{"latitude":42.350754,"longitude":-71.04276},"isZillowOwned":false,"flexFieldText":"149 days on Zillow","flexFieldType":"daysOnZillow","hdpData":{"homeInfo":{"zpid":2055520175,"streetAddress":"150 Seaport Blvd #5A","zipcode":"02210","city":"Boston","state":"MA","latitude":42.350754,"longitude":-71.04276,"price":2100000,"datePriceChanged":1711436400000,"bathrooms":2,"bedrooms":1,"livingArea":996,"homeType":"CONDO","homeStatus":"FOR_SALE","daysOnZillow":150,"isFeatured":false,"shouldHighlight":false,"zestimate":1997700,"rentZestimate":8075,"listing_sub_type":{"is_FSBA":true},"priceReduction":"","isUnmappable":false,"isPreforeclosureAuction":false,"homeStatusForHDP":"FOR_SALE","priceForHDP":2100000,"priceChange":-145000,"timeOnZillow":13011907000,"isNonOwnerOccupied":true,"isPremierBuilder":false,"isZillowOwned":false,"currency":"USD","country":"USA","unit":"# 5A","lotAreaValue":0,"lotAreaUnit":"sqft","isShowcaseListing":false}},"isSaved":false,"isUserClaimingOwner":false,"isUserConfirmedClaim":false,"pgapt":"ForSale","sgapt":"For Sale (Broker)","zestimate":1997700.0,"shouldShowZestimateAsPrice":false,"has3DModel":false,"hasVideo":false,"isHomeRec":false,"hasAdditionalAttributions":false,"isFeaturedListing":false,"isShowcaseListing":false,"list":true,"relaxed":false,"info6String":null,"brokerName":null,"carouselPhotos":[{"url":"https:\/\/photos.zillowstatic.com\/fp\/b900fb776103f539bce3970880772889-p_e.jpg"},{"url":"https:\/\/photos.zillowstatic.com\/fp\/1012eb3a904ed0eee75a37458d2b541f-p_e.jpg"},{"url":"https:\/\/photos.zillowstatic.com\/fp\/cd0b8c0e800e1baab485466006ca0255-p_e.jpg"},{"url":"https:\/\/photos.zillowstatic.com\/fp\/8dca23085aad3a3755915fd346d71c5d-p_e.jpg"},{"url":"https:\/\/photos.zillowstatic.com\/fp\/ccb1bfff10f113158f876b06658b77c7-p_e.jpg"},{"url":"https:\/\/photos.zillowstatic.com\/fp\/724c893f1dba820a66b54a53a7624790-p_e.jpg"},{"url":"https:\/\/photos.zillowstatic.com\/fp\/701a67d849d14cd76d4302e5a3813d57-p_e.jpg"},{"url":"https:\/\/photos.zillowstatic.com\/fp\/ef3b2030d35848d8a3538a90311df0d2-p_e.jpg"},{"url":"https:\/\/photos.zillowstatic.com\/fp\/bb4d17f982c7e2478ed157982de811d3-p_e.jpg"},{"url":"https:\/\/photos.zillowstatic.com\/fp\/4d327cf74dd7448a54874ccc6b3258c5-p_e.jpg"},{"url":"https:\/\/photos.zillowstatic.com\/fp\/9d488f28a866eaea1d7160c19251657b-p_e.jpg"},{"url":"https:\/\/photos.zillowstatic.com\/fp\/4d7893920cd1569974914e340a5bac6e-p_e.jpg"},{"url":"https:\/\/photos.zillowstatic.com\/fp\/44e01084f6ce83172ab0f3f4226e0e72-p_e.jpg"},{"url":"https:\/\/photos.zillowstatic.com\/fp\/ce3e6b61fd7657408b35e71e026264bf-p_e.jpg"},{"url":"https:\/\/photos.zillowstatic.com\/fp\/e4dfea64d1a95e670bc52f434505584b-p_e.jpg"},{"url":"https:\/\/photos.zillowstatic.com\/fp\/f25586495921ff104b83af1feb68c471-p_e.jpg"},{"url":"https:\/\/photos.zillowstatic.com\/fp\/35b2c0272bfe88a0c21e4b821ab174ac-p_e.jpg"},{"url":"https:\/\/photos.zillowstatic.com\/fp\/ef78d1c19f4b1c6ad0719a23526e4a42-p_e.jpg"},{"url":"https:\/\/photos.zillowstatic.com\/fp\/8cdf3ddd4de605a61b4b53f33b7bde63-p_e.jpg"},{"url":"https:\/\/photos.zillowstatic.com\/fp\/166eb5f84d68b9306d88ebe03c8efe41-p_e.jpg"},{"url":"https:\/\/photos.zillowstatic.com\/fp\/6f5b1ca511bb7ab7115e676a68eb3e5a-p_e.jpg"},{"url":"https:\/\/photos.zillowstatic.com\/fp\/ee4ad70effa74cb5a2793cea7ae92cfd-p_e.jpg"},{"url":"https:\/\/photos.zillowstatic.com\/fp\/104225c92566a7a753f3107b14472243-p_e.jpg"},{"url":"https:\/\/photos.zillowstatic.com\/fp\/10fa759294cfa4f35904fe876a0f0e8c-p_e.jpg"},{"url":"https:\/\/photos.zillowstatic.com\/fp\/536c0c138f1fb477ce036dd2d578b973-p_e.jpg"}]}
{"zpid":"239893096","id":"239893096","rawHomeStatusCd":"ForSale","marketingStatusSimplifiedCd":"For Sale by Agent","imgSrc":"https:\/\/photos.zillowstatic.com\/fp\/ffd0344d6b44fbf4dbcc09f2a93c6727-p_e.jpg","hasImage":true,"detailUrl":"https:\/\/www.zillow.com\/homedetails\/22-Liberty-Dr-UNIT-5D-Boston-MA-02210\/239893096_zpid\/","statusType":"FOR_SALE","statusText":"Condo for sale","countryCurrency":"$","price":"$5,360,000","unformattedPrice":5360000,"address":"22 Liberty Dr UNIT 5D, Boston, MA 02210","addressStreet":"22 Liberty Dr UNIT 5D","addressCity":"Boston","addressState":"MA","addressZipcode":"02210","isUndisclosedAddress":false,"beds":2,"baths":3,"area":1985,"latLong":{"latitude":42.354733,"longitude":-71.04564},"isZillowOwned":false,"flexFieldText":"Price cut: $40,000 (Jul 08)","flexFieldType":"priceCut","hdpData":{"homeInfo":{"zpid":239893096,"streetAddress":"22 Liberty Dr UNIT 5D","zipcode":"02210","city":"Boston","state":"MA","latitude":42.354733,"longitude":-71.04564,"price":5360000,"datePriceChanged":1720422000000,"bathrooms":3,"bedrooms":2,"livingArea":1985,"homeType":"CONDO","homeStatus":"FOR_SALE","daysOnZillow":121,"isFeatured":false,"shouldHighlight":false,"zestimate":5055600,"rentZestimate":21363,"listing_sub_type":{"is_FSBA":true},"priceReduction":"$40,000 (Jul 8)","isUnmappable":false,"isPreforeclosureAuction":false,"homeStatusForHDP":"FOR_SALE","priceForHDP":5360000,"priceChange":-40000,"timeOnZillow":10506307000,"isNonOwnerOccupied":true,"isPremierBuilder":false,"isZillowOwned":false,"currency":"USD","country":"USA","taxAssessedValue":3860400,"unit":"Unit 5D","lotAreaValue":0,"lotAreaUnit":"sqft","isShowcaseListing":false}},"isSaved":false,"isUserClaimingOwner":false,"isUserConfirmedClaim":false,"pgapt":"ForSale","sgapt":"For Sale (Broker)","zestimate":5055600.0,"shouldShowZestimateAsPrice":false,"has3DModel":false,"hasVideo":false,"isHomeRec":false,"hasAdditionalAttributions":false,"isFeaturedListing":false,"isShowcaseListing":false,"list":true,"relaxed":false,"info6String":null,"brokerName":null,"carouselPhotos":[{"url":"https:\/\/photos.zillowstatic.com\/fp\/ffd0344d6b44fbf4dbcc09f2a93c6727-p_e.jpg"},{"url":"https:\/\/photos.zillowstatic.com\/fp\/0087acd6ead954e38463843d2c9ee0ad-p_e.jpg"},{"url":"https:\/\/photos.zillowstatic.com\/fp\/72df34fedc4908e4cb865dd55ff95877-p_e.jpg"},{"url":"https:\/\/photos.zillowstatic.com\/fp\/be47e4605adc80d73a5c8482925d966e-p_e.jpg"},{"url":"https:\/\/photos.zillowstatic.com\/fp\/5d0817f776f7697380b926e84f943292-p_e.jpg"},{"url":"https:\/\/photos.zillowstatic.com\/fp\/501b6c443ac31da95177775551c5469b-p_e.jpg"},{"url":"https:\/\/photos.zillowstatic.com\/fp\/f63c96512e17b8cd58863f2d764711c8-p_e.jpg"},{"url":"https:\/\/photos.zillowstatic.com\/fp\/acbba9bab11276f2602b860601d37c40-p_e.jpg"},{"url":"https:\/\/photos.zillowstatic.com\/fp\/b5731a4b62ab7345757b95dcb4f81e4e-p_e.jpg"},{"url":"https:\/\/photos.zillowstatic.com\/fp\/c406e50a2174d11697ab4ec80b8cd548-p_e.jpg"},{"url":"https:\/\/photos.zillowstatic.com\/fp\/fa57ceceb51d5b6aff4c7cf9f137d931-p_e.jpg"},{"url":"https:\/\/photos.zillowstatic.com\/fp\/5e2dc03e073632ae31cfcbd3e61f2ae4-p_e.jpg"},{"url":"https:\/\/photos.zillowstatic.com\/fp\/e6653c05097e26182f0b5909bd1a04f1-p_e.jpg"},{"url":"https:\/\/photos.zillowstatic.com\/fp\/271143c43a602f2285bdbe92ef656293-p_e.jpg"},{"url":"https:\/\/photos.zillowstatic.com\/fp\/df60559dcbd63d908ed98d358cd25be9-p_e.jpg"},{"url":"https:\/\/photos.zillowstatic.com\/fp\/0f2413d91c8f83a42cb162c5e9633db1-p_e.jpg"},{"url":"https:\/\/photos.zillowstatic.com\/fp\/98f7e4320220a40d7d57b014b8b31f24-p_e.jpg"},{"url":"https:\/\/photos.zillowstatic.com\/fp\/0c232bf6be2436c8ec3ac540e9f9f58d-p_e.jpg"},{"url":"https:\/\/photos.zillowstatic.com\/fp\/84b25845623465637c8017e017392fc2-p_e.jpg"},{"url":"https:\/\/photos.zillowstatic.com\/fp\/895131e0585e1c9878c231ce7c5d2fc9-p_e.jpg"},{"url":"https:\/\/photos.zillowstatic.com\/fp\/82627c26c4a53f24f6b6bcdd938dfdf5-p_e.jpg"},{"url":"https:\/\/photos.zillowstatic.com\/fp\/77b0902be4a37dadd151d7613cabd85b-p_e.jpg"},{"url":"https:\/\/photos.zillowstatic.com\/fp\/ca7c564a9d084f00d9a515e5187bf601-p_e.jpg"},{"url":"https:\/\/photos.zillowstatic.com\/fp\/21fcdb27fe7a8c7f6f802d4685d58d58-p_e.jpg"},{"url":"https:\/\/photos.zillowstatic.com\/fp\/b994562a58c15d669e2f162a1738027a-p_e.jpg"}]}
{"zpid":"81858801","id":"81858801","rawHomeStatusCd":"ForSale","marketingStatusSimplifiedCd":"For Sale by Agent","imgSrc":"https:\/\/photos.zillowstatic.com\/fp\/012964ec435467d705610ceffeaa605a-p_e.jpg","hasImage":true,"detailUrl":"https:\/\/www.zillow.com\/homedetails\/500-Atlantic-Ave-UNIT-21C-Boston-MA-02210\/81858801_zpid\/","statusType":"FOR_SALE","statusText":"Condo for sale","countryCurrency":"$","price":"$1,295,000","unformattedPrice":1295000,"address":"500 Atlantic Ave UNIT 21C, Boston, MA 02210","addressStreet":"500 Atlantic Ave UNIT 21C","addressCity":"Boston","addressState":"MA","addressZipcode":"02210","isUndisclosedAddress":false,"beds":1,"baths":2,"area":1060,"latLong":{"latitude":42.353855,"longitude":-71.052},"isZillowOwned":false,"flexFieldText":"78 days on Zillow","flexFieldType":"daysOnZillow","hdpData":{"homeInfo":{"zpid":81858801,"streetAddress":"500 Atlantic Ave UNIT 21C","zipcode":"02210","city":"Boston","state":"MA","latitude":42.353855,"longitude":-71.052,"price":1295000,"datePriceChanged":1717052400000,"bathrooms":2,"bedrooms":1,"livingArea":1060,"homeType":"CONDO","homeStatus":"FOR_SALE","daysOnZillow":78,"isFeatured":false,"shouldHighlight":false,"zestimate":1236900,"rentZestimate":4500,"listing_sub_type":{"is_FSBA":true},"priceReduction":"$54,000 (May 30)","isUnmappable":false,"isPreforeclosureAuction":false,"homeStatusForHDP":"FOR_SALE","priceForHDP":1295000,"priceChange":-54000,"timeOnZillow":6791107000,"isNonOwnerOccupied":true,"isPremierBuilder":false,"isZillowOwned":false,"currency":"USD","country":"USA","taxAssessedValue":1261000,"unit":"Unit 21C","isShowcaseListing":false}},"isSaved":false,"isUserClaimingOwner":false,"isUserConfirmedClaim":false,"pgapt":"ForSale","sgapt":"For Sale (Broker)","zestimate":1236900.0,"shouldShowZestimateAsPrice":false,"has3DModel":false,"hasVideo":false,"isHomeRec":false,"hasAdditionalAttributions":true,"isFeaturedListing":false,"isShowcaseListing":false,"list":true,"relaxed":false,"info6String":"Jillian Adler","brokerName":"Compass","carouselPhotos":[{"url":"https:\/\/photos.zillowstatic.com\/fp\/012964ec435467d705610ceffeaa605a-p_e.jpg"},{"url":"https:\/\/photos.zillowstatic.com\/fp\/83f83ecb3e032c557f4ed81586e25c52-p_e.jpg"},{"url":"https:\/\/photos.zillowstatic.com\/fp\/2cad0fc9ff7569a5f61e0da7fabdddcf-p_e.jpg"},{"url":"https:\/\/photos.zillowstatic.com\/fp\/0f659961ae8b6826cfe325b167de64b3-p_e.jpg"},{"url":"https:\/\/photos.zillowstatic.com\/fp\/0c794d9ac207bbd39cc8d586dcaec5c1-p_e.jpg"},{"url":"https:\/\/photos.zillowstatic.com\/fp\/e2f47a9e39a05afef66a55653887754d-p_e.jpg"},{"url":"https:\/\/photos.zillowstatic.com\/fp\/5c76e5e44d6d6485b25205fe85bf6e7c-p_e.jpg"},{"url":"https:\/\/photos.zillowstatic.com\/fp\/a52deeda76ff65efdacec8bb2af7820c-p_e.jpg"},{"url":"https:\/\/photos.zillowstatic.com\/fp\/c2435fad2aebd2c269ffa85566eedce4-p_e.jpg"},{"url":"https:\/\/photos.zillowstatic.com\/fp\/7590aabeb63428fd94d3914ff9b60885-p_e.jpg"},{"url":"https:\/\/photos.zillowstatic.com\/fp\/2f677518c4a383616c9691e14dc8b2e2-p_e.jpg"},{"url":"https:\/\/photos.zillowstatic.com\/fp\/3ae5e4172d0673ebdab3e398f1bb0e0a-p_e.jpg"},{"url":"https:\/\/photos.zillowstatic.com\/fp\/700c55ca11943587736a8f2e88bfde49-p_e.jpg"},{"url":"https:\/\/photos.zillowstatic.com\/fp\/0c0523688ee67c1c3a8f818db0ac732b-p_e.jpg"},{"url":"https:\/\/photos.zillowstatic.com\/fp\/2ec9a654abe59d179a96fdcf78c9a069-p_e.jpg"},{"url":"https:\/\/photos.zillowstatic.com\/fp\/b3d18d04fc3a7eb41e2c7972cff03c40-p_e.jpg"},{"url":"https:\/\/photos.zillowstatic.com\/fp\/78041805391ca4ecf11cd06cc0050140-p_e.jpg"},{"url":"https:\/\/photos.zillowstatic.com\/fp\/7ae7f30f25fc491b658e5af6d5aaf8f3-p_e.jpg"},{"url":"https:\/\/photos.zillowstatic.com\/fp\/9d63997ef8f392f64fbcdeadedd1aa19-p_e.jpg"},{"url":"https:\/\/photos.zillowstatic.com\/fp\/c58de930e4a9f3c31bc6496b258ab42c-p_e.jpg"},{"url":"https:\/\/photos.zillowstatic.com\/fp\/b6bc4d0b67322b3c9d4ea4e07d8b0fad-p_e.jpg"},{"url":"https:\/\/photos.zillowstatic.com\/fp\/d5e8c889313003da4dbb4d5bfde4f031-p_e.jpg"},{"url":"https:\/\/photos.zillowstatic.com\/fp\/818f349a5b7ad239b46f0301f477aef9-p_e.jpg"},{"url":"https:\/\/photos.zillowstatic.com\/fp\/7bb96413d9ca7acbf82dec3e9ab76c6e-p_e.jpg"}]}
{"zpid":"351055187","id":"351055187","rawHomeStatusCd":"ForSale","marketingStatusSimplifiedCd":"For Sale by Agent","imgSrc":"https:\/\/photos.zillowstatic.com\/fp\/874f323b375918a5cda6a6a2e886fed0-p_e.jpg","hasImage":true,"detailUrl":"https:\/\/www.zillow.com\/homedetails\/150-Seaport-Blvd-PENTHOUSE-2G-Boston-MA-02210\/351055187_zpid\/","statusType":"FOR_SALE","statusText":"Condo for sale","countryCurrency":"$","price":"$2,199,000","unformattedPrice":2199000,"address":"150 Seaport Blvd PENTHOUSE 2G, Boston, MA 02210","addressStreet":"150 Seaport Blvd PENTHOUSE 2G","addressCity":"Boston","addressState":"MA","addressZipcode":"02210","isUndisclosedAddress":false,"beds":1,"baths":2,"area":968,"latLong":{"latitude":42.350754,"longitude":-71.04276},"isZillowOwned":false,"flexFieldText":"58 days on Zillow","flexFieldType":"daysOnZillow","hdpData":{"homeInfo":{"zpid":351055187,"streetAddress":"150 Seaport Blvd PENTHOUSE 2G","zipcode":"02210","city":"Boston","state":"MA","latitude":42.350754,"longitude":-71.04276,"price":2199000,"bathrooms":2,"bedrooms":1,"livingArea":968,"homeType":"CONDO","homeStatus":"FOR_SALE","daysOnZillow":59,"isFeatured":false,"shouldHighlight":false,"listing_sub_type":{"is_FSBA":true},"isUnmappable":false,"isPreforeclosureAuction":false,"homeStatusForHDP":"FOR_SALE","priceForHDP":2199000,"timeOnZillow":5149507000,"isNonOwnerOccupied":true,"isPremierBuilder":false,"isZillowOwned":false,"currency":"USD","country":"USA","unit":"Penthouse 2G","isShowcaseListing":false}},"isSaved":false,"isUserClaimingOwner":false,"isUserConfirmedClaim":false,"pgapt":"ForSale","sgapt":"For Sale (Broker)","zestimate":null,"shouldShowZestimateAsPrice":false,"has3DModel":false,"hasVideo":false,"isHomeRec":false,"hasAdditionalAttributions":true,"isFeaturedListing":false,"isShowcaseListing":false,"list":true,"relaxed":false,"info6String":"Michael Moynihan","brokerName":"TCC \/ St. Regis Residences","carouselPhotos":[{"url":"https:\/\/photos.zillowstatic.com\/fp\/874f323b375918a5cda6a6a2e886fed0-p_e.jpg"},{"url":"https:\/\/photos.zillowstatic.com\/fp\/a20fe4ad9c30916cf46b1748402e3cba-p_e.jpg"},{"url":"https:\/\/photos.zillowstatic.com\/fp\/80b9975a524f00507a5851d4fece508d-p_e.jpg"},{"url":"https:\/\/photos.zillowstatic.com\/fp\/1b53efcb5a153df4749a3260614d960a-p_e.jpg"},{"url":"https:\/\/photos.zillowstatic.com\/fp\/f29db47dcf45461d09fa526748501b84-p_e.jpg"},{"url":"https:\/\/photos.zillowstatic.com\/fp\/fce8e2fd97c46baae5b06abea77367fa-p_e.jpg"},{"url":"https:\/\/photos.zillowstatic.com\/fp\/c7b7b99a88d3fc9493132ecbb1a811d1-p_e.jpg"},{"url":"https:\/\/photos.zillowstatic.com\/fp\/7762d7a0e747b7e7ee152fc12fffbfc8-p_e.jpg"},{"url":"https:\/\/photos.zillowstatic.com\/fp\/47fafee9699867d16df1aa078c3599e4-p_e.jpg"},{"url":"https:\/\/photos.zillowstatic.com\/fp\/7c4139cfcd4af3990b4d927368184ce5-p_e.jpg"},{"url":"https:\/\/photos.zillowstatic.com\/fp\/5454adcaec657df18194aea9c57eeebb-p_e.jpg"},{"url":"https:\/\/photos.zillowstatic.com\/fp\/3fad61f048e86c3f2c82816061041c92-p_e.jpg"},{"url":"https:\/\/photos.zillowstatic.com\/fp\/6c280186b733d6223b837e3cf9c2ee5f-p_e.jpg"},{"url":"https:\/\/photos.zillowstatic.com\/fp\/241caf86794e0a60f920df4ea9950fc4-p_e.jpg"},{"url":"https:\/\/photos.zillowstatic.com\/fp\/49ef3faa7abce2eb9dd0f30c448bc9bb-p_e.jpg"},{"url":"https:\/\/photos.zillowstatic.com\/fp\/4f7ab7ac3070efea4562e2eae56f6579-p_e.jpg"},{"url":"https:\/\/photos.zillowstatic.com\/fp\/7bfdfea32ead5364c47e137f6bf21fa6-p_e.jpg"},{"url":"https:\/\/photos.zillowstatic.com\/fp\/c232f15de4ac84154d7f41ded948a39d-p_e.jpg"}]}
{"zpid":"318226262","id":"318226262","rawHomeStatusCd":"ForSale","marketingStatusSimplifiedCd":"For Sale by Agent","imgSrc":"https:\/\/photos.zillowstatic.com\/fp\/54020d75f652c98d2e0f5956f979510b-p_e.jpg","hasImage":true,"detailUrl":"https:\/\/www.zillow.com\/homedetails\/50-Liberty-Dr-UNIT-9H-Boston-MA-02210\/318226262_zpid\/","statusType":"FOR_SALE","statusText":"Condo for sale","countryCurrency":"$","price":"$2,500,000","unformattedPrice":2500000,"address":"50 Liberty Dr UNIT 9H, Boston, MA 02210","addressStreet":"50 Liberty Dr UNIT 9H","addressCity":"Boston","addressState":"MA","addressZipcode":"02210","isUndisclosedAddress":false,"beds":1,"baths":2,"area":946,"latLong":{"latitude":42.354156,"longitude":-71.044525},"isZillowOwned":false,"flexFieldText":"170 days on Zillow","flexFieldType":"daysOnZillow","hdpData":{"homeInfo":{"zpid":318226262,"streetAddress":"50 Liberty Dr UNIT 9H","zipcode":"02210","city":"Boston","state":"MA","latitude":42.354156,"longitude":-71.044525,"price":2500000,"bathrooms":2,"bedrooms":1,"livingArea":946,"homeType":"CONDO","homeStatus":"FOR_SALE","daysOnZillow":171,"isFeatured":false,"shouldHighlight":false,"zestimate":2374200,"rentZestimate":9552,"listing_sub_type":{"is_FSBA":true},"isUnmappable":false,"isPreforeclosureAuction":false,"homeStatusForHDP":"FOR_SALE","priceForHDP":2500000,"timeOnZillow":14826307000,"isNonOwnerOccupied":true,"isPremierBuilder":false,"isZillowOwned":false,"currency":"USD","country":"USA","taxAssessedValue":1070800,"unit":"Unit 9H","lotAreaValue":0,"lotAreaUnit":"sqft","isShowcaseListing":false}},"isSaved":false,"isUserClaimingOwner":false,"isUserConfirmedClaim":false,"pgapt":"ForSale","sgapt":"For Sale (Broker)","zestimate":2374200.0,"shouldShowZestimateAsPrice":false,"has3DModel":false,"hasVideo":false,"isHomeRec":false,"hasAdditionalAttributions":false,"isFeaturedListing":false,"isShowcaseListing":false,"list":true,"relaxed":false,"info6String":null,"brokerName":null,"carouselPhotos":[{"url":"https:\/\/photos.zillowstatic.com\/fp\/54020d75f652c98d2e0f5956f979510b-p_e.jpg"},{"url":"https:\/\/photos.zillowstatic.com\/fp\/431a1d8e56476c043e65561bbb4d65ad-p_e.jpg"},{"url":"https:\/\/photos.zillowstatic.com\/fp\/7e889ddf3aee7881113342c50a0ca530-p_e.jpg"},{"url":"https:\/\/photos.zillowstatic.com\/fp\/8b0e8013ca12dbf3e666149bce8a92e9-p_e.jpg"},{"url":"https:\/\/photos.zillowstatic.com\/fp\/da5723f408eec144e52ec59936b290d3-p_e.jpg"},{"url":"https:\/\/photos.zillowstatic.com\/fp\/7db86658f7673fb119e0e58913a52107-p_e.jpg"},{"url":"https:\/\/photos.zillowstatic.com\/fp\/1a8be90058a6da5dcc06591bd28f63ec-p_e.jpg"},{"url":"https:\/\/photos.zillowstatic.com\/fp\/1ed6d596c8523cec942cd68df55f68bf-p_e.jpg"},{"url":"https:\/\/photos.zillowstatic.com\/fp\/0012a89e38a5fd7f5738992553ffa337-p_e.jpg"},{"url":"https:\/\/photos.zillowstatic.com\/fp\/97f672dfce90b4db5c931d92122bdef3-p_e.jpg"},{"url":"https:\/\/photos.zillowstatic.com\/fp\/da8960aac8bd57e59c6c7aaaac6faae9-p_e.jpg"},{"url":"https:\/\/photos.zillowstatic.com\/fp\/50d03d5fb7fb17aa0f424e14939795a1-p_e.jpg"},{"url":"https:\/\/photos.zillowstatic.com\/fp\/274efe442bd53ba3c818fe56cc2f5138-p_e.jpg"},{"url":"https:\/\/photos.zillowstatic.com\/fp\/5419b1b24fe48a13f545a146d7cf6904-p_e.jpg"},{"url":"https:\/\/photos.zillowstatic.com\/fp\/a3404687274da6e02b368e1fbc73d421-p_e.jpg"},{"url":"https:\/\/photos.zillowstatic.com\/fp\/7d23ef07ab6bb20b7610668000d7148d-p_e.jpg"}]}
{"zpid":"333605974","id":"333605974","rawHomeStatusCd":"ForSale","marketingStatusSimplifiedCd":"For Sale by Agent","imgSrc":"https:\/\/photos.zillowstatic.com\/fp\/d8cef58d4db6fec5429c415c4690d6e8-p_e.jpg","hasImage":true,"detailUrl":"https:\/\/www.zillow.com\/homedetails\/133-Seaport-Blvd-705-Boston-MA-02210\/333605974_zpid\/","statusType":"FOR_SALE","statusText":"Condo for sale","countryCurrency":"$","price":"$1,450,000","unformattedPrice":1450000,"address":"133 Seaport Blvd #705, Boston, MA 02210","addressStreet":"133 Seaport Blvd #705","addressCity":"Boston","addressState":"MA","addressZipcode":"02210","isUndisclosedAddress":false,"beds":1,"baths":2,"area":812,"latLong":{"latitude":42.35051,"longitude":-71.04362},"isZillowOwned":false,"flexFieldText":"84 days on Zillow","flexFieldType":"daysOnZillow","hdpData":{"homeInfo":{"zpid":333605974,"streetAddress":"133 Seaport Blvd #705","zipcode":"02210","city":"Boston","state":"MA","latitude":42.35051,"longitude":-71.04362,"price":1450000,"bathrooms":2,"bedrooms":1,"livingArea":812,"homeType":"CONDO","homeStatus":"FOR_SALE","daysOnZillow":85,"isFeatured":false,"shouldHighlight":false,"zestimate":1388200,"rentZestimate":5786,"listing_sub_type":{"is_FSBA":true},"isUnmappable":false,"isPreforeclosureAuction":false,"homeStatusForHDP":"FOR_SALE","priceForHDP":1450000,"timeOnZillow":7395907000,"isNonOwnerOccupied":true,"isPremierBuilder":false,"isZillowOwned":false,"currency":"USD","country":"USA","taxAssessedValue":1227100,"unit":"# 705","isShowcaseListing":false}},"isSaved":false,"isUserClaimingOwner":false,"isUserConfirmedClaim":false,"pgapt":"ForSale","sgapt":"For Sale (Broker)","zestimate":1388200.0,"shouldShowZestimateAsPrice":false,"has3DModel":false,"hasVideo":false,"isHomeRec":false,"hasAdditionalAttributions":true,"isFeaturedListing":false,"isShowcaseListing":false,"list":true,"relaxed":false,"info6String":"Nicholas Mattia","brokerName":"Luxury Residential Group, LLC","carouselPhotos":[{"url":"https:\/\/photos.zillowstatic.com\/fp\/d8cef58d4db6fec5429c415c4690d6e8-p_e.jpg"},{"url":"https:\/\/photos.zillowstatic.com\/fp\/ce80b380e8e285694d459b647a974408-p_e.jpg"},{"url":"https:\/\/photos.zillowstatic.com\/fp\/162bda85ada29338b82b9514e59a4972-p_e.jpg"},{"url":"https:\/\/photos.zillowstatic.com\/fp\/8e15612a92130c8e5f13761bf55b309b-p_e.jpg"},{"url":"https:\/\/photos.zillowstatic.com\/fp\/a418720da3d2572987707cb1b702e85b-p_e.jpg"},{"url":"https:\/\/photos.zillowstatic.com\/fp\/b6c6bef0c21f8a558aefe0a7298e9059-p_e.jpg"},{"url":"https:\/\/photos.zillowstatic.com\/fp\/07dc8afc31724c10e49e557fff1dc376-p_e.jpg"},{"url":"https:\/\/photos.zillowstatic.com\/fp\/201f08adb95815a9f738057f36934290-p_e.jpg"},{"url":"https:\/\/photos.zillowstatic.com\/fp\/8a03078856cfa99b83ac87b5b859da32-p_e.jpg"},{"url":"https:\/\/photos.zillowstatic.com\/fp\/71257d52852fedf63525b233e9095c92-p_e.jpg"},{"url":"https:\/\/photos.zillowstatic.com\/fp\/b8fbf8a956d59eaf543747fc18a640f1-p_e.jpg"}]}
{"zpid":"349900064","id":"349900064","rawHomeStatusCd":"ForSale","marketingStatusSimplifiedCd":"For Sale by Agent","imgSrc":"https:\/\/photos.zillowstatic.com\/fp\/ec7131788c31a691ee238714a4b76e21-p_e.jpg","hasImage":true,"detailUrl":"https:\/\/www.zillow.com\/homedetails\/150-Seaport-Blvd-7D-Boston-MA-02210\/349900064_zpid\/","statusType":"FOR_SALE","statusText":"Condo for sale","countryCurrency":"$","price":"$3,899,000","unformattedPrice":3899000,"address":"150 Seaport Blvd #7D, Boston, MA 02210","addressStreet":"150 Seaport Blvd #7D","addressCity":"Boston","addressState":"MA","addressZipcode":"02210","isUndisclosedAddress":false,"beds":2,"baths":3,"area":1752,"latLong":{"latitude":42.350754,"longitude":-71.04276},"isZillowOwned":false,"flexFieldText":"72 days on Zillow","flexFieldType":"daysOnZillow","hdpData":{"homeInfo":{"zpid":349900064,"streetAddress":"150 Seaport Blvd #7D","zipcode":"02210","city":"Boston","state":"MA","latitude":42.350754,"longitude":-71.04276,"price":3899000,"bathrooms":3,"bedrooms":2,"livingArea":1752,"homeType":"CONDO","homeStatus":"FOR_SALE","daysOnZillow":73,"isFeatured":false,"shouldHighlight":false,"listing_sub_type":{"is_FSBA":true},"isUnmappable":false,"isPreforeclosureAuction":false,"homeStatusForHDP":"FOR_SALE","priceForHDP":3899000,"timeOnZillow":6359107000,"isNonOwnerOccupied":true,"isPremierBuilder":false,"isZillowOwned":false,"currency":"USD","country":"USA","unit":"# 7D","isShowcaseListing":false}},"isSaved":false,"isUserClaimingOwner":false,"isUserConfirmedClaim":false,"pgapt":"ForSale","sgapt":"For Sale (Broker)","zestimate":null,"shouldShowZestimateAsPrice":false,"has3DModel":false,"hasVideo":false,"isHomeRec":false,"hasAdditionalAttributions":true,"isFeaturedListing":false,"isShowcaseListing":false,"list":true,"relaxed":false,"info6String":"Michael Moynihan","brokerName":"TCC \/ St. Regis Residences","carouselPhotos":[{"url":"https:\/\/photos.zillowstatic.com\/fp\/ec7131788c31a691ee238714a4b76e21-p_e.jpg"},{"url":"https:\/\/photos.zillowstatic.com\/fp\/dfbd26c68b48ddc0c546f87c06185be4-p_e.jpg"},{"url":"https:\/\/photos.zillowstatic.com\/fp\/dbfa4147048157827a5fcf83ba32e476-p_e.jpg"},{"url":"https:\/\/photos.zillowstatic.com\/fp\/2521b6aaea72c3dfe406001546e52843-p_e.jpg"},{"url":"https:\/\/photos.zillowstatic.com\/fp\/8ad7d2ab3b67614a4f6d58b0434980c6-p_e.jpg"},{"url":"https:\/\/photos.zillowstatic.com\/fp\/245991d5244f35e8d2569a1e7702950a-p_e.jpg"},{"url":"https:\/\/photos.zillowstatic.com\/fp\/0b3052f823dcc9bbfe20e0edfbf39121-p_e.jpg"},{"url":"https:\/\/photos.zillowstatic.com\/fp\/dccc9989c36daecff1e81e53b1258ae4-p_e.jpg"},{"url":"https:\/\/photos.zillowstatic.com\/fp\/5aeea5dac1783e6e6f4d93a53551b203-p_e.jpg"},{"url":"https:\/\/photos.zillowstatic.com\/fp\/8c35dd0e8c2851740561962dab904d28-p_e.jpg"},{"url":"https:\/\/photos.zillowstatic.com\/fp\/80de10eb1dcb3d7aac899acf143a6527-p_e.jpg"},{"url":"https:\/\/photos.zillowstatic.com\/fp\/bef6eb90121e9eb624f91aa12117bf29-p_e.jpg"},{"url":"https:\/\/photos.zillowstatic.com\/fp\/d291d9d54998a6e0d3ba318a460f90ac-p_e.jpg"},{"url":"https:\/\/photos.zillowstatic.com\/fp\/8576e9c95cf63c4a8522645748cdb327-p_e.jpg"},{"url":"https:\/\/photos.zillowstatic.com\/fp\/8b838461c73954035c2d60f69c56fa93-p_e.jpg"},{"url":"https:\/\/photos.zillowstatic.com\/fp\/9c925520e8f4ae6581fa51de31d464ee-p_e.jpg"},{"url":"https:\/\/photos.zillowstatic.com\/fp\/fbdc084707b22dd0ab39f79b69514dc3-p_e.jpg"},{"url":"https:\/\/photos.zillowstatic.com\/fp\/bea787c65dcf597b928028ad1fd63df7-p_e.jpg"},{"url":"https:\/\/photos.zillowstatic.com\/fp\/daf459768ee26074a742374681208256-p_e.jpg"}]}
{"zpid":"2059768165","id":"2059768165","rawHomeStatusCd":"ForSale","marketingStatusSimplifiedCd":"For Sale by Agent","imgSrc":"https:\/\/photos.zillowstatic.com\/fp\/6618d42f8a9da901449bbd2048f55e51-p_e.jpg","hasImage":true,"detailUrl":"https:\/\/www.zillow.com\/homedetails\/150-Seaport-Blvd-11A-Boston-MA-02210\/2059768165_zpid\/","statusType":"FOR_SALE","statusText":"Condo for sale","countryCurrency":"$","price":"$2,539,000","unformattedPrice":2539000,"address":"150 Seaport Blvd #11A, Boston, MA 02210","addressStreet":"150 Seaport Blvd #11A","addressCity":"Boston","addressState":"MA","addressZipcode":"02210","isUndisclosedAddress":false,"beds":1,"baths":2,"area":1128,"latLong":{"latitude":42.350754,"longitude":-71.04276},"isZillowOwned":false,"flexFieldText":"149 days on Zillow","flexFieldType":"daysOnZillow","hdpData":{"homeInfo":{"zpid":2059768165,"streetAddress":"150 Seaport Blvd #11A","zipcode":"02210","city":"Boston","state":"MA","latitude":42.350754,"longitude":-71.04276,"price":2539000,"bathrooms":2,"bedrooms":1,"livingArea":1128,"homeType":"CONDO","homeStatus":"FOR_SALE","daysOnZillow":150,"isFeatured":false,"shouldHighlight":false,"zestimate":2411200,"rentZestimate":10019,"listing_sub_type":{"is_FSBA":true},"isUnmappable":false,"isPreforeclosureAuction":false,"homeStatusForHDP":"FOR_SALE","priceForHDP":2539000,"timeOnZillow":13011907000,"isNonOwnerOccupied":true,"isPremierBuilder":false,"isZillowOwned":false,"currency":"USD","country":"USA","unit":"# 11A","lotAreaValue":0,"lotAreaUnit":"sqft","isShowcaseListing":false}},"isSaved":false,"isUserClaimingOwner":false,"isUserConfirmedClaim":false,"pgapt":"ForSale","sgapt":"For Sale (Broker)","zestimate":2411200.0,"shouldShowZestimateAsPrice":false,"has3DModel":false,"hasVideo":false,"isHomeRec":false,"hasAdditionalAttributions":false,"isFeaturedListing":false,"isShowcaseListing":false,"list":true,"relaxed":false,"info6String":null,"brokerName":null,"carouselPhotos":[{"url":"https:\/\/photos.zillowstatic.com\/fp\/6618d42f8a9da901449bbd2048f55e51-p_e.jpg"},{"url":"https:\/\/photos.zillowstatic.com\/fp\/48b05ed9c81e7c2b6e7f0b872821ec80-p_e.jpg"},{"url":"https:\/\/photos.zillowstatic.com\/fp\/f045539474efcb3beec0cd4b25108c52-p_e.jpg"},{"url":"https:\/\/photos.zillowstatic.com\/fp\/be2c4d546c06ad2fe7d31e03d0743126-p_e.jpg"},{"url":"https:\/\/photos.zillowstatic.com\/fp\/401b4f1ae786ffdeb0291a474b6ab0a9-p_e.jpg"},{"url":"https:\/\/photos.zillowstatic.com\/fp\/4e14ce53579e52612fddbe3ac18d6e99-p_e.jpg"},{"url":"https:\/\/photos.zillowstatic.com\/fp\/075c8baaf8651852fad07ae953802745-p_e.jpg"},{"url":"https:\/\/photos.zillowstatic.com\/fp\/fbc7f15039d25b4bf3279b62a0a44b8e-p_e.jpg"},{"url":"https:\/\/photos.zillowstatic.com\/fp\/68cf64de8471457618e337e93405cb8d-p_e.jpg"},{"url":"https:\/\/photos.zillowstatic.com\/fp\/4b74d9501764de1cf3b597f89aa3d786-p_e.jpg"},{"url":"https:\/\/photos.zillowstatic.com\/fp\/9f1921189f5d6207ee17345c749e551a-p_e.jpg"},{"url":"https:\/\/photos.zillowstatic.com\/fp\/210ab4a70813d8c17c7af27b45488b8d-p_e.jpg"},{"url":"https:\/\/photos.zillowstatic.com\/fp\/3adebd096b5f97258ca251dd5437f963-p_e.jpg"},{"url":"https:\/\/photos.zillowstatic.com\/fp\/5d3804eae4e4804f371c1872021c3d0b-p_e.jpg"},{"url":"https:\/\/photos.zillowstatic.com\/fp\/67868bca282142c1ef78f973975d26e8-p_e.jpg"},{"url":"https:\/\/photos.zillowstatic.com\/fp\/942d3e28664446566c363ee2d24a6e32-p_e.jpg"},{"url":"https:\/\/photos.zillowstatic.com\/fp\/e4dfea64d1a95e670bc52f434505584b-p_e.jpg"},{"url":"https:\/\/photos.zillowstatic.com\/fp\/f25586495921ff104b83af1feb68c471-p_e.jpg"},{"url":"https:\/\/photos.zillowstatic.com\/fp\/ee4ad70effa74cb5a2793cea7ae92cfd-p_e.jpg"},{"url":"https:\/\/photos.zillowstatic.com\/fp\/35b2c0272bfe88a0c21e4b821ab174ac-p_e.jpg"},{"url":"https:\/\/photos.zillowstatic.com\/fp\/ef78d1c19f4b1c6ad0719a23526e4a42-p_e.jpg"},{"url":"https:\/\/photos.zillowstatic.com\/fp\/8cdf3ddd4de605a61b4b53f33b7bde63-p_e.jpg"},{"url":"https:\/\/photos.zillowstatic.com\/fp\/166eb5f84d68b9306d88ebe03c8efe41-p_e.jpg"},{"url":"https:\/\/photos.zillowstatic.com\/fp\/6f5b1ca511bb7ab7115e676a68eb3e5a-p_e.jpg"},{"url":"https:\/\/photos.zillowstatic.com\/fp\/104225c92566a7a753f3107b14472243-p_e.jpg"},{"url":"https:\/\/photos.zillowstatic.com\/fp\/10fa759294cfa4f35904fe876a0f0e8c-p_e.jpg"},{"url":"https:\/\/photos.zillowstatic.com\/fp\/536c0c138f1fb477ce036dd2d578b973-p_e.jpg"},{"url":"https:\/\/photos.zillowstatic.com\/fp\/6622f5d6e69c3fb8110169375bba537d-p_e.jpg"}]}
